{
	"nodes": [
		{
			"nodeId": "119",
			"type": "token",
			"text": "stateProperty",
			"parentId":"118"
		},
		{
			"nodeId": "118",
			"type": "rule",
			"ruleIndex": "27",
			"parentId":"117"
		},
		{
			"nodeId": "120",
			"type": "token",
			"text": ".",
			"parentId":"117"
		},
		{
			"nodeId": "121",
			"type": "token",
			"text": "addPropertyChangeListener",
			"parentId":"117"
		},
		{
			"nodeId": "122",
			"type": "token",
			"text": "(",
			"parentId":"117"
		},
		{
			"nodeId": "143",
			"type": "token",
			"text": "new",
			"parentId":"142"
		},
		{
			"nodeId": "144",
			"type": "token",
			"text": "SimpleDataViewerListener",
			"parentId":"142"
		},
		{
			"nodeId": "145",
			"type": "token",
			"text": "(",
			"parentId":"142"
		},
		{
			"nodeId": "164",
			"type": "token",
			"text": "firstNamePanel",
			"parentId":"163"
		},
		{
			"nodeId": "163",
			"type": "rule",
			"ruleIndex": "29",
			"parentId":"162"
		},
		{
			"nodeId": "162",
			"type": "rule",
			"ruleIndex": "231",
			"parentId":"161"
		},
		{
			"nodeId": "161",
			"type": "rule",
			"ruleIndex": "230",
			"parentId":"160"
		},
		{
			"nodeId": "160",
			"type": "rule",
			"ruleIndex": "227",
			"parentId":"159"
		},
		{
			"nodeId": "159",
			"type": "rule",
			"ruleIndex": "226",
			"parentId":"158"
		},
		{
			"nodeId": "158",
			"type": "rule",
			"ruleIndex": "225",
			"parentId":"157"
		},
		{
			"nodeId": "157",
			"type": "rule",
			"ruleIndex": "224",
			"parentId":"156"
		},
		{
			"nodeId": "156",
			"type": "rule",
			"ruleIndex": "223",
			"parentId":"155"
		},
		{
			"nodeId": "155",
			"type": "rule",
			"ruleIndex": "222",
			"parentId":"154"
		},
		{
			"nodeId": "154",
			"type": "rule",
			"ruleIndex": "221",
			"parentId":"153"
		},
		{
			"nodeId": "153",
			"type": "rule",
			"ruleIndex": "220",
			"parentId":"152"
		},
		{
			"nodeId": "152",
			"type": "rule",
			"ruleIndex": "219",
			"parentId":"151"
		},
		{
			"nodeId": "151",
			"type": "rule",
			"ruleIndex": "218",
			"parentId":"150"
		},
		{
			"nodeId": "150",
			"type": "rule",
			"ruleIndex": "217",
			"parentId":"149"
		},
		{
			"nodeId": "149",
			"type": "rule",
			"ruleIndex": "216",
			"parentId":"148"
		},
		{
			"nodeId": "148",
			"type": "rule",
			"ruleIndex": "212",
			"parentId":"147"
		},
		{
			"nodeId": "147",
			"type": "rule",
			"ruleIndex": "207",
			"parentId":"146"
		},
		{
			"nodeId": "146",
			"type": "rule",
			"ruleIndex": "199",
			"parentId":"142"
		},
		{
			"nodeId": "165",
			"type": "token",
			"text": ")",
			"parentId":"142"
		},
		{
			"nodeId": "142",
			"type": "rule",
			"ruleIndex": "188",
			"parentId":"141"
		},
		{
			"nodeId": "141",
			"type": "rule",
			"ruleIndex": "183",
			"parentId":"140"
		},
		{
			"nodeId": "140",
			"type": "rule",
			"ruleIndex": "176",
			"parentId":"139"
		},
		{
			"nodeId": "139",
			"type": "rule",
			"ruleIndex": "231",
			"parentId":"138"
		},
		{
			"nodeId": "138",
			"type": "rule",
			"ruleIndex": "230",
			"parentId":"137"
		},
		{
			"nodeId": "137",
			"type": "rule",
			"ruleIndex": "227",
			"parentId":"136"
		},
		{
			"nodeId": "136",
			"type": "rule",
			"ruleIndex": "226",
			"parentId":"135"
		},
		{
			"nodeId": "135",
			"type": "rule",
			"ruleIndex": "225",
			"parentId":"134"
		},
		{
			"nodeId": "134",
			"type": "rule",
			"ruleIndex": "224",
			"parentId":"133"
		},
		{
			"nodeId": "133",
			"type": "rule",
			"ruleIndex": "223",
			"parentId":"132"
		},
		{
			"nodeId": "132",
			"type": "rule",
			"ruleIndex": "222",
			"parentId":"131"
		},
		{
			"nodeId": "131",
			"type": "rule",
			"ruleIndex": "221",
			"parentId":"130"
		},
		{
			"nodeId": "130",
			"type": "rule",
			"ruleIndex": "220",
			"parentId":"129"
		},
		{
			"nodeId": "129",
			"type": "rule",
			"ruleIndex": "219",
			"parentId":"128"
		},
		{
			"nodeId": "128",
			"type": "rule",
			"ruleIndex": "218",
			"parentId":"127"
		},
		{
			"nodeId": "127",
			"type": "rule",
			"ruleIndex": "217",
			"parentId":"126"
		},
		{
			"nodeId": "126",
			"type": "rule",
			"ruleIndex": "216",
			"parentId":"125"
		},
		{
			"nodeId": "125",
			"type": "rule",
			"ruleIndex": "212",
			"parentId":"124"
		},
		{
			"nodeId": "124",
			"type": "rule",
			"ruleIndex": "207",
			"parentId":"123"
		},
		{
			"nodeId": "123",
			"type": "rule",
			"ruleIndex": "199",
			"parentId":"117"
		},
		{
			"nodeId": "166",
			"type": "token",
			"text": ")",
			"parentId":"117"
		},
		{
			"nodeId": "117",
			"type": "rule",
			"ruleIndex": "196",
			"parentId":"116"
		},
		{
			"nodeId": "116",
			"type": "rule",
			"ruleIndex": "138",
			"parentId":"115"
		},
		{
			"nodeId": "167",
			"type": "token",
			"text": ";",
			"parentId":"115"
		},
		{
			"nodeId": "115",
			"type": "rule",
			"ruleIndex": "137",
			"parentId":"114"
		},
		{
			"nodeId": "114",
			"type": "rule",
			"ruleIndex": "133",
			"parentId":"113"
		},
		{
			"nodeId": "113",
			"type": "rule",
			"ruleIndex": "131",
			"parentId":"112"
		},
		{
			"nodeId": "112",
			"type": "rule",
			"ruleIndex": "128",
			"parentId": "-1"
		}
	]
}
